{
    "Version": "1.2",
    "Data": {
        "Source": "e:\\viscalivelinkdev\\plugins\\livelinkvisca\\source\\livelinkvisca\\private\\livelinkvisca.cpp",
        "ProvidedModule": "",
        "PCH": "e:\\viscalivelinkdev\\intermediate\\build\\win64\\x64\\viscalivelinkdeveditor\\development\\unrealed\\sharedpch.unrealed.cpp20.h.pch",
        "Includes": [
            "e:\\viscalivelinkdev\\plugins\\livelinkvisca\\intermediate\\build\\win64\\x64\\unrealeditor\\development\\livelinkvisca\\definitions.livelinkvisca.h",
            "e:\\viscalivelinkdev\\plugins\\livelinkvisca\\source\\livelinkvisca\\public\\livelinkvisca.h"
        ],
        "ImportedModules": [],
        "ImportedHeaderUnits": []
    }
}